openAiWrapper/__init__.py
openAiWrapper/decorator.py
openaiwrapperfunction-0.1.2.dist-info/licenses/LICENSE
openaiwrapperfunction-0.1.2.dist-info/METADATA
openaiwrapperfunction-0.1.2.dist-info/WHEEL
openaiwrapperfunction-0.1.2.dist-info/top_level.txt
openaiwrapperfunction-0.1.2.dist-info/RECORD
