Metadata-Version: 2.4
Name: openaiWrapperFunction
Version: 0.1.2
Summary: Decorator for creating OpenAI function tools
Home-page: https://github.com/pilot4u/openaiWrapper
Author: David Lerner
Author-email: mr.david.lerner@gmail.com
Classifier: Programming Language :: Python :: 3
Classifier: License :: OSI Approved :: MIT License
Classifier: Operating System :: OS Independent
Requires-Python: >=3.8
License-File: LICENSE
Requires-Dist: openai
Dynamic: author
Dynamic: author-email
Dynamic: classifier
Dynamic: description
Dynamic: description-content-type
Dynamic: home-page
Dynamic: license-file
Dynamic: requires-dist
Dynamic: requires-python
Dynamic: summary
